LICENSE
sqlalchemy2strawberry/__init__.py
sqlalchemy2strawberry/main.py
sqlalchemy2strawberry-0.0.1.dist-info/LICENSE
sqlalchemy2strawberry-0.0.1.dist-info/WHEEL
sqlalchemy2strawberry-0.0.1.dist-info/METADATA
sqlalchemy2strawberry-0.0.1.dist-info/RECORD
